tsercom/__init__.py
tsercom/_version.py
tsercom/discovery_e2etest.py
tsercom/rpc_e2etest.py
tsercom/runtime_e2etest.py
tsercom/api/__init__.py
tsercom/api/initialization_pair.py
tsercom/api/runtime_command.py
tsercom/api/runtime_factory_factory.py
tsercom/api/runtime_handle.py
tsercom/api/runtime_manager.py
tsercom/api/runtime_manager_helpers.py
tsercom/api/runtime_manager_unittest.py
tsercom/api/local_process/__init__.py
tsercom/api/local_process/local_runtime_factory.py
tsercom/api/local_process/local_runtime_factory_factory.py
tsercom/api/local_process/local_runtime_factory_factory_unittest.py
tsercom/api/local_process/local_runtime_factory_unittest.py
tsercom/api/local_process/runtime_command_bridge.py
tsercom/api/local_process/runtime_command_bridge_unittest.py
tsercom/api/local_process/runtime_wrapper.py
tsercom/api/local_process/runtime_wrapper_unittest.py
tsercom/api/split_process/__init__.py
tsercom/api/split_process/data_reader_sink.py
tsercom/api/split_process/data_reader_sink_unittest.py
tsercom/api/split_process/data_reader_source.py
tsercom/api/split_process/data_reader_source_unittest.py
tsercom/api/split_process/event_source.py
tsercom/api/split_process/event_source_unittest.py
tsercom/api/split_process/remote_runtime_factory.py
tsercom/api/split_process/remote_runtime_factory_unittest.py
tsercom/api/split_process/runtime_command_source.py
tsercom/api/split_process/runtime_command_source_unittest.py
tsercom/api/split_process/shim_runtime_handle.py
tsercom/api/split_process/shim_runtime_handle_unittest.py
tsercom/api/split_process/split_process_error_watcher_sink.py
tsercom/api/split_process/split_process_error_watcher_sink_unittest.py
tsercom/api/split_process/split_process_error_watcher_source.py
tsercom/api/split_process/split_process_error_watcher_source_unittest.py
tsercom/api/split_process/split_runtime_factory_factory.py
tsercom/api/split_process/split_runtime_factory_factory_unittest.py
tsercom/caller_id/__init__.py
tsercom-1.1.3.dist-info/licenses/LICENSE
tsercom-1.1.3.dist-info/METADATA
tsercom-1.1.3.dist-info/WHEEL
tsercom-1.1.3.dist-info/top_level.txt
tsercom-1.1.3.dist-info/RECORD
