Metadata-Version: 2.4
Name: tsercom
Version: 1.1.3
Summary: Time-SERies COMmunication using gRPC for data science and machine learning applications.
Author: Ryan Keane
License: Apache-2.0
Project-URL: Homepage, https://github.com/rwkeane/tsercom
Project-URL: Documentation, https://github.com/rwkeane/tsercom
Project-URL: Repository, https://github.com/rwkeane/tsercom
Project-URL: Issues, https://github.com/rwkeane/tsercom/issues
Keywords: ts,time,time series,communication,rpc,serialization,transport,channel,grpc
Classifier: Programming Language :: Python
Classifier: Programming Language :: Python :: 3
Classifier: Programming Language :: Python :: 3.10
Classifier: Programming Language :: Python :: 3.11
Classifier: Programming Language :: Python :: 3.12
Classifier: License :: OSI Approved :: Apache Software License
Requires-Python: >=3.10
License-File: LICENSE
Requires-Dist: grpcio<1.74.0,>=1.62.0
Requires-Dist: grpcio-status<1.74.0,>=1.62.0
Requires-Dist: grpcio-tools<1.74.0,>=1.62.0
Requires-Dist: ntplib>=0.4.0
Requires-Dist: zeroconf>=0.135.0
Requires-Dist: psutil>=5.9.0
Provides-Extra: dev
Requires-Dist: pytest; extra == "dev"
Requires-Dist: pytest-asyncio; extra == "dev"
Requires-Dist: pytest-mock; extra == "dev"
Requires-Dist: pytest-timeout; extra == "dev"
Requires-Dist: pre-commit; extra == "dev"
Requires-Dist: ruff; extra == "dev"
Requires-Dist: black; extra == "dev"
Requires-Dist: mypy; extra == "dev"
Requires-Dist: pylint; extra == "dev"
Requires-Dist: cryptography; extra == "dev"
Requires-Dist: mypy-protobuf; extra == "dev"
Provides-Extra: typing
Requires-Dist: types-psutil; extra == "typing"
Requires-Dist: types-requests; extra == "typing"
Requires-Dist: mypy-protobuf; extra == "typing"
Provides-Extra: docs
Requires-Dist: sphinx; extra == "docs"
Requires-Dist: sphinx-rtd-theme; extra == "docs"
Requires-Dist: sphinx-multiversion; extra == "docs"
Dynamic: license-file
